sorodev/__init__.py
sorodev/__main__.py
sorodev/account.py
sorodev/add_contract.py
sorodev/bindings.py
sorodev/build.py
sorodev/constants.py
sorodev/deploy.py
sorodev/install.py
sorodev/invoke.py
sorodev/test.py
sorodev/utils.py
sorodev-0.0.2.dist-info/LICENSE
sorodev-0.0.2.dist-info/METADATA
sorodev-0.0.2.dist-info/WHEEL
sorodev-0.0.2.dist-info/entry_points.txt
sorodev-0.0.2.dist-info/RECORD
