Metadata-Version: 2.1
Name: sorodev
Version: 0.0.2
Summary: Develop with soroban more efficiently
License: GPL-3.0-only
Author: flokapi
Author-email: flokapi@pm.me
Requires-Python: >=3.7,<4.0
Classifier: License :: OSI Approved :: GNU General Public License v3 (GPLv3)
Classifier: Programming Language :: Python :: 3
Classifier: Programming Language :: Python :: 3.7
Classifier: Programming Language :: Python :: 3.8
Classifier: Programming Language :: Python :: 3.9
Classifier: Programming Language :: Python :: 3.10
Classifier: Programming Language :: Python :: 3.11
Classifier: Programming Language :: Python :: 3.12
Requires-Dist: platformdirs
Requires-Dist: pyyaml
Project-URL: documentation, https://github.com/flokapi/sorodev
Project-URL: homepage, https://github.com/flokapi/sorodev
Project-URL: repository, https://github.com/flokapi/sorodev
